[
  {
    "email": "nbrvc11222@hotmail.com",
    "password": "RVdE5JjDWs",
    "region": "US"
  },
  {
    "email": "dpkjknd45561@hotmail.com",
    "password": "UnM6JFrANs",
    "region": "US"
  },
  {
    "email": "zojmbtx70164@hotmail.com",
    "password": "T9f82c6jUE",
    "region": "US"
  },
  {
    "email": "myzpena@hotmail.com",
    "password": "EUscZ1Vb74",
    "region": "US"
  },
  {
    "email": "vloywp03721@hotmail.com",
    "password": "Aa121314",
    "region": "US"
  },
  {
    "email": "ehfubfm81714@hotmail.com",
    "password": "SQAM3qTWQ7",
    "region": "KR"
  },
  {
    "email": "meliannieal3950@hotmail.com",
    "password": "Hyy1cNtYrh",
    "region": "VN"
  },
  {
    "email": "vavaedgae97613@hotmail.com",
    "password": "Aa121314",
    "region": "HK"
  },
  {
    "email": "m8g3tucker@hotmail.com",
    "password": "srmuhTh86Z",
    "region": "TW"
  },
  {
    "email": "asaees48r0ecj@hotmail.com",
    "password": "V686BZx1gn",
    "region": "JP"
  },
  {
    "email": "valdezhalimaneziaok@gmail.com",
    "password": "Bb223322",
    "region": "HK"
  },
  {
    "email": "sabrinari3234@hotmail.com",
    "password": "TDSKtjUWwX4E",
    "region": "US"
  },
  {
    "email": "lajlaolesen4283@hotmail.com",
    "password": "TDxUwR54Dk6m",
    "region": "US"
  },
  {
    "email": "miminaana3593@hotmail.com",
    "password": "TDTEQzz4nPU8",
    "region": "US"
  },
  {
    "email": "charitoseir2661@hotmail.com",
    "password": "TDCWCWeZVh2y",
    "region": "US"
  },
  {
    "email": "maricarli8144@hotmail.com",
    "password": "TDazWWhzXP3F",
    "region": "VN"
  },
  {
    "email": "beateliz8126@hotmail.com",
    "password": "TDCBd3FgyHBx",
    "region": "US"
  },
  {
    "email": "3034@lvoeky.com",
    "password": "AGnFCbeEb8",
    "region": "VN"
  },
  {
    "email": "3009@lvoeky.com",
    "password": "mv1ERPN7cM",
    "region": "US"
  },
  {
    "email": "3031@lvoeky.com",
    "password": "GgsAtu63QM",
    "region": "US"
  },
  {
    "email": "3020@lvoeky.com",
    "password": "X7p6HGjum4",
    "region": "US"
  },
  {
    "email": "3006@lvoeky.com",
    "password": "FhUcpBaf3A",
    "region": "US"
  },
  {
    "email": "3015@lvoeky.com",
    "password": "16sZn4fGxm",
    "region": "US"
  },
  {
    "email": "3022@lvoeky.com",
    "password": "5K877kVj2g",
    "region": "HK"
  },
  {
    "email": "quodonnell@gmail.com",
    "password": "Dd10096da",
    "region": "US"
  },
  {
    "email": "rosskennedyjreg5953@gmail.com",
    "password": "De1Hm1h7a9",
    "region": "US"
  },
  {
    "email": "pamela53chadwickmjj@outlook.com",
    "password": "ef6BRTCpTj",
    "region": "US"
  },
  {
    "email": "robertwang380@gmail.com",
    "password": "fgKXq3uWA6",
    "region": "US"
  },
  {
    "email": "VedderEarlrbpjhf@gmail.com",
    "password": "4PdNahXmqR",
    "region": "US"
  },
  {
    "email": "miastnley@gmail.com",
    "password": "Dd13c8e6d",
    "region": "US"
  },
  {
    "email": "michelleqmrwi3@gmail.com",
    "password": "gM7H6p96py",
    "region": "US"
  },
  {
    "email": "DeborazpiHarr967@icloud.com",
    "password": "x5Qt9ch9m9",
    "region": "US"
  },
  {
    "email": "PerezBettyzzd@gmail.com",
    "password": "98uXd9NR7w",
    "region": "US"
  },
  {
    "email": "bradtnrosalbav39153@gmail.com",
    "password": "6jRNZT41Bm",
    "region": "US"
  },
  {
    "email": "qfvblj2968@163.com",
    "password": "1qNQ2sDUJ1",
    "region": "US"
  },
  {
    "email": "madelyncravenlgzx5364@gmail.com",
    "password": "vN151Vd7Dy",
    "region": "US"
  },
  {
    "email": "kwopigk3809@163.com",
    "password": "Dd128c2e6",
    "region": "US"
  },
  {
    "email": "MirandzpiHugh848@icloud.com",
    "password": "spkV7Q52C1",
    "region": "US"
  },
  {
    "email": "KevizpiMe644@icloud.com",
    "password": "jBh1Vj8EH3",
    "region": "US"
  },
  {
    "email": "REBELPRIDE79@hotmail.com",
    "password": "6CFTdyJpNA",
    "region": "US"
  },
  {
    "email": "orprobeso50@outlook.com",
    "password": "6EJG1crZbk",
    "region": "US"
  },
  {
    "email": "lambertruth282@gmail.com",
    "password": "2fCnKFRFKR",
    "region": "US"
  },
  {
    "email": "BettyGarcia5be56@gmail.com",
    "password": "44s4nrRa3yZnJ5",
    "region": "US"
  },
  {
    "email": "vgilesgh42@gmail.com",
    "password": "4HWwRkya6B",
    "region": "US"
  },
  {
    "email": "jyvqvepn475@163.com",
    "password": "TDvU2c8Yw9Qr",
    "region": "US"
  },
  {
    "email": "AllenMilliepyl879@gmail.com",
    "password": "44s41NP3MD5pf3",
    "region": "US"
  },
  {
    "email": "qian2007495zhan@163.com",
    "password": "CkMNTrafY8",
    "region": "US"
  },
  {
    "email": "stevensnjjt1@gmail.com",
    "password": "FP5a6bmVH4",
    "region": "US"
  },
  {
    "email": "jarvarisrivetteuf3409@gmail.com",
    "password": "VG7j2eeg4C",
    "region": "US"
  },
  {
    "email": "uchtredmagowandf5018@gmail.com",
    "password": "Y3B9gtum4K",
    "region": "US"
  },
  {
    "email": "andersenproschvc2764@gmail.com",
    "password": "FAy8cCAE8R",
    "region": "US"
  },
  {
    "email": "qgb477203@163.com",
    "password": "cZK7zCHkFF",
    "region": "US"
  },
  {
    "email": "rowenawoodard246042b@icloud.com",
    "password": "BgW5juwnAt",
    "region": "US"
  },
  {
    "email": "qfpcwzp942@163.com",
    "password": "mxhp8mP9BJ",
    "region": "US"
  },
  {
    "email": "ancq61nufio@gmail.com",
    "password": "Ma3ZMvZu2w",
    "region": "US"
  },
  {
    "email": "jy359840651@163.com",
    "password": "Dd1927013",
    "region": "US"
  },
  {
    "email": "tieshamorwaywi6420@gmail.com",
    "password": "6ZRcWustJ4",
    "region": "US"
  }
]