{
  "timestamp": 1774530076,
  "data": {
    "accounts": {
      "group1": [
        {
          "id": "1-1",
          "fullEmail": "watkinskimbejenni9c5@icloud.com",
          "password": "jrU4CfkWCY",
          "status": "正常",
          "checkTime": "2026-03-26 20:44:35",
          "region": "US",
          "regionName": "美国"
        },
        {
          "id": "1-2",
          "fullEmail": "suzanngonzalez7x5@icloud.com",
          "password": "M7MVSKhY6F",
          "status": "正常",
          "checkTime": "2026-03-26 20:40:56",
          "region": "US",
          "regionName": "中国大陆"
        },
        {
          "id": "1-3",
          "fullEmail": "ptayjones4k7@icloud.com",
          "password": "H9EwgaHaDC",
          "status": "正常",
          "checkTime": "2026-03-26 20:36:46",
          "region": "US",
          "regionName": "美国"
        },
        {
          "id": "1-4",
          "fullEmail": "cshersalas1x1@icloud.com",
          "password": "5PMbg2WDhp",
          "status": "正常",
          "checkTime": "2026-03-26 20:43:55",
          "region": "US",
          "regionName": "美国"
        },
        {
          "id": "1-5",
          "fullEmail": "josepbaldwin8g1@icloud.com",
          "password": "9HfZU5zd4a",
          "status": "正常",
          "checkTime": "2026-03-26 20:44:22",
          "region": "US",
          "regionName": "美国"
        },
        {
          "id": "1-6",
          "fullEmail": "valerigeorge5x2@icloud.com",
          "password": "e3cEUkngJm",
          "status": "正常",
          "checkTime": "2026-03-26 20:43:55",
          "region": "US",
          "regionName": "中国大陆"
        },
        {
          "id": "1-7",
          "fullEmail": "ericarepowell9q4@icloud.com",
          "password": "FUeMChNH8S",
          "status": "正常",
          "checkTime": "2026-03-26 20:39:25",
          "region": "US",
          "regionName": "美国"
        },
        {
          "id": "1-8",
          "fullEmail": "douglasoto9c6@icloud.com",
          "password": "K5MSu5DJpJ",
          "status": "正常",
          "checkTime": "2026-03-26 20:43:54",
          "region": "US",
          "regionName": "美国"
        },
        {
          "id": "1-9",
          "fullEmail": "sabrinaturdennis7l6@icloud.com",
          "password": "9Z5Xh1GJ1x",
          "status": "正常",
          "checkTime": "2026-03-26 20:36:50",
          "region": "US",
          "regionName": "美国"
        },
        {
          "id": "1-10",
          "fullEmail": "btayaguilar2h9@icloud.com",
          "password": "QyX51pEEtq",
          "status": "正常",
          "checkTime": "2026-03-26 20:43:54",
          "region": "US",
          "regionName": "美国"
        },
        {
          "id": "1-11",
          "fullEmail": "derehoffman4n3@icloud.com",
          "password": "HK7rBA6YtN",
          "status": "正常",
          "checkTime": "2026-03-26 20:39:50",
          "region": "US",
          "regionName": "美国"
        },
        {
          "id": "1-12",
          "fullEmail": "jeffharhughes5w9@icloud.com",
          "password": "1UFaYdVrgM",
          "status": "正常",
          "checkTime": "2026-03-26 20:44:27",
          "region": "US",
          "regionName": "美国"
        },
        {
          "id": "1-13",
          "fullEmail": "torreschristopzim8l8@icloud.com",
          "password": "R35qqRN3Kn",
          "status": "正常",
          "checkTime": "2026-03-26 20:43:54",
          "region": "US",
          "regionName": "美国"
        },
        {
          "id": "1-14",
          "fullEmail": "robermartinez1c9@icloud.com",
          "password": "jbf79XgGDU",
          "status": "正常",
          "checkTime": "2026-03-26 20:37:27",
          "region": "US",
          "regionName": "美国"
        },
        {
          "id": "1-15",
          "fullEmail": "reillyjestokes8s1@icloud.com",
          "password": "TQt7ZZaEHv",
          "status": "正常",
          "checkTime": "2026-03-26 20:42:27",
          "region": "US",
          "regionName": "美国"
        },
        {
          "id": "1-16",
          "fullEmail": "whitetbrown1k7@icloud.com",
          "password": "dxWmuP4mCM",
          "status": "正常",
          "checkTime": "2026-03-26 20:38:29",
          "region": "US",
          "regionName": "美国"
        },
        {
          "id": "1-17",
          "fullEmail": "michaelcoocohen7z3@icloud.com",
          "password": "kEKNSyH1Ff",
          "status": "正常",
          "checkTime": "2026-03-26 20:44:36",
          "region": "US",
          "regionName": "美国"
        },
        {
          "id": "1-18",
          "fullEmail": "sarahmasjohnson3h4@icloud.com",
          "password": "xwmP7b6kVs",
          "status": "正常",
          "checkTime": "2026-03-26 20:43:27",
          "region": "US",
          "regionName": "美国"
        },
        {
          "id": "1-19",
          "fullEmail": "gregorymichlindse2u3@icloud.com",
          "password": "CNgs2Pj2Ss",
          "status": "正常",
          "checkTime": "2026-03-26 20:39:26",
          "region": "US",
          "regionName": "美国"
        },
        {
          "id": "1-20",
          "fullEmail": "thmann7z8@icloud.com",
          "password": "acwC1ZSjyv",
          "status": "正常",
          "checkTime": "2026-03-26 20:38:27",
          "region": "US",
          "regionName": "美国"
        },
        {
          "id": "1-21",
          "fullEmail": "harrisjoscrawford9v5@icloud.com",
          "password": "fbR41WzUJ8",
          "status": "正常",
          "checkTime": "2026-03-26 20:38:31",
          "region": "US",
          "regionName": "美国"
        },
        {
          "id": "1-22",
          "fullEmail": "amandabrsmith7j8@icloud.com",
          "password": "wRn2vJ9x6p",
          "status": "正常",
          "checkTime": "2026-03-26 20:38:24",
          "region": "US",
          "regionName": "美国"
        },
        {
          "id": "1-23",
          "fullEmail": "jeffreysimmrobins4v9@icloud.com",
          "password": "8WRfUUAANP",
          "status": "正常",
          "checkTime": "2026-03-26 20:38:26",
          "region": "US",
          "regionName": "美国"
        },
        {
          "id": "1-24",
          "fullEmail": "nicoledunn1149@iCloud.com",
          "password": "aKtFaQX7Pv",
          "status": "正常",
          "checkTime": "2026-03-26 20:35:49",
          "region": "US",
          "regionName": "美国"
        },
        {
          "id": "1-25",
          "fullEmail": "jameswilson0453@iCloud.com",
          "password": "xJTRtCgF66",
          "status": "正常",
          "checkTime": "2026-03-26 20:36:13",
          "region": "US",
          "regionName": "美国"
        },
        {
          "id": "1-26",
          "fullEmail": "nbrvc11222@hotmail.com",
          "password": "RVdE5JjDWs",
          "status": "正常",
          "checkTime": "2025-11-07 12:22:45",
          "region": "US",
          "regionName": "美国"
        },
        {
          "id": "1-27",
          "fullEmail": "dpkjknd45561@hotmail.com",
          "password": "UnM6JFrANs",
          "status": "正常",
          "checkTime": "2025-11-07 12:39:02",
          "region": "US",
          "regionName": "美国"
        },
        {
          "id": "1-28",
          "fullEmail": "julianmauhudson@outlook.com",
          "password": "TDzt3zWvPD7q",
          "status": "正常",
          "checkTime": "2026-03-26 20:44:26",
          "region": "VN",
          "regionName": "越南"
        },
        {
          "id": "1-29",
          "fullEmail": "eliasu2riley@outlook.com",
          "password": "TDSV8FP7gHxk",
          "status": "正常",
          "checkTime": "2026-03-26 20:15:29",
          "region": "US",
          "regionName": "美国"
        },
        {
          "id": "1-30",
          "fullEmail": "ibulqbg720235@icloud.com",
          "password": "feJty4H68E",
          "status": "正常",
          "checkTime": "2026-03-26 20:44:56",
          "region": "VN",
          "regionName": "越南"
        },
        {
          "id": "1-31",
          "fullEmail": "walesks12@icloud.com",
          "password": "qvhyQ5KUsJ",
          "status": "正常",
          "checkTime": "2026-03-26 20:46:04",
          "region": "US",
          "regionName": "美国"
        },
        {
          "id": "1-32",
          "fullEmail": "ocgcewr235137@icloud.com",
          "password": "Sx5WadrhvT",
          "status": "正常",
          "checkTime": "2026-03-26 20:45:53",
          "region": "VN",
          "regionName": "越南"
        },
        {
          "id": "1-33",
          "fullEmail": "yrltpph440994@icloud.com",
          "password": "vF1xKtGzZ9",
          "status": "正常",
          "checkTime": "2026-03-26 20:42:00",
          "region": "MY",
          "regionName": "马来西亚"
        },
        {
          "id": "1-34",
          "fullEmail": "ousdxpf261614@icloud.com",
          "password": "jgSTv1ZDQ1",
          "status": "正常",
          "checkTime": "2026-03-26 20:43:37",
          "region": "RU",
          "regionName": "俄罗斯"
        },
        {
          "id": "1-35",
          "fullEmail": "zvmksii070361@icloud.com",
          "password": "rgNt45nHch",
          "status": "正常",
          "checkTime": "2026-03-26 20:41:44",
          "region": "US",
          "regionName": "美国"
        },
        {
          "id": "1-36",
          "fullEmail": "bvjlkvh111332@icloud.com",
          "password": "epUQm6RjKG",
          "status": "正常",
          "checkTime": "2026-03-26 18:48:46",
          "region": "VN",
          "regionName": "越南"
        },
        {
          "id": "1-37",
          "fullEmail": "rwvidmf934559@icloud.com",
          "password": "9jfvZapAJb",
          "status": "正常",
          "checkTime": "2026-03-26 20:41:53",
          "region": "SG",
          "regionName": "新加坡"
        },
        {
          "id": "1-38",
          "fullEmail": "dsgirlv551049@icloud.com",
          "password": "twz62K9tTf",
          "status": "正常",
          "checkTime": "2026-03-26 20:44:47",
          "region": "US",
          "regionName": "阿根廷"
        },
        {
          "id": "1-39",
          "fullEmail": "hgtmckw876484@icloud.com",
          "password": "Av6pfpwgax",
          "status": "正常",
          "checkTime": "2026-03-26 20:25:00",
          "region": "US",
          "regionName": "土耳其"
        },
        {
          "id": "1-40",
          "fullEmail": "wu985826536225@icloud.com",
          "password": "3qMUFpSvzT",
          "status": "正常",
          "checkTime": "2026-03-26 20:44:42",
          "region": "US",
          "regionName": "澳大利亚"
        },
        {
          "id": "1-41",
          "fullEmail": "huai284600975@icloud.com",
          "password": "dGj85mhf2f",
          "status": "正常",
          "checkTime": "2026-03-26 20:33:12",
          "region": "TW",
          "regionName": "台湾"
        },
        {
          "id": "1-42",
          "fullEmail": "clqqfri393972@icloud.com",
          "password": "2rGR2TwxAP",
          "status": "正常",
          "checkTime": "2026-03-26 20:45:08",
          "region": "RU",
          "regionName": "俄罗斯"
        },
        {
          "id": "1-43",
          "fullEmail": "alswlln389627@icloud.com",
          "password": "ba1b9K5X84",
          "status": "正常",
          "checkTime": "2026-03-26 20:30:14",
          "region": "MY",
          "regionName": "马来西亚"
        },
        {
          "id": "1-44",
          "fullEmail": "cushbyp873765@icloud.com",
          "password": "hGThgDf4gn",
          "status": "正常",
          "checkTime": "2026-03-26 20:43:19",
          "region": "US",
          "regionName": "美国"
        },
        {
          "id": "1-45",
          "fullEmail": "tornayjmc@icloud.com",
          "password": "Z3mRdJqRXw",
          "status": "正常",
          "checkTime": "2026-03-26 20:37:06",
          "region": "SG",
          "regionName": "新加坡"
        },
        {
          "id": "1-46",
          "fullEmail": "puaelwg676696@icloud.com",
          "password": "1GQNAQV1Yk",
          "status": "正常",
          "checkTime": "2026-03-26 20:32:57",
          "region": "US",
          "regionName": "美国"
        },
        {
          "id": "1-47",
          "fullEmail": "afcvthg218414@icloud.com",
          "password": "Cu49Y4WhbX",
          "status": "正常",
          "checkTime": "2026-03-26 20:40:33",
          "region": "KR",
          "regionName": "韩国"
        },
        {
          "id": "1-48",
          "fullEmail": "kdzibli335026@icloud.com",
          "password": "ht92DcBgHf",
          "status": "正常",
          "checkTime": "2026-03-26 20:45:15",
          "region": "US",
          "regionName": "美国"
        },
        {
          "id": "1-49",
          "fullEmail": "nwqmlkm724113@icloud.com",
          "password": "HapaXex6TJ",
          "status": "正常",
          "checkTime": "2026-03-26 20:42:44",
          "region": "VN",
          "regionName": "越南"
        },
        {
          "id": "1-50",
          "fullEmail": "lhjksvl709436@icloud.com",
          "password": "Vrwuy3TU3D",
          "status": "正常",
          "checkTime": "2026-03-26 20:42:35",
          "region": "US",
          "regionName": "美国"
        },
        {
          "id": "1-51",
          "fullEmail": "spmrkit094953@icloud.com",
          "password": "XG9bY3kSAf",
          "status": "正常",
          "checkTime": "2026-03-26 20:45:19",
          "region": "US",
          "regionName": "中国大陆"
        },
        {
          "id": "1-52",
          "fullEmail": "eyizmyq936626@icloud.com",
          "password": "yWsHb1Pqhk",
          "status": "正常",
          "checkTime": "2026-03-26 20:43:45",
          "region": "US",
          "regionName": "澳大利亚"
        }
      ],
      "group2": []
    },
    "vpn_ads": [
      {
        "id": "vpn-1",
        "name": "宝可梦VPN",
        "features": "新起之秀。本推广链接注册后，每月赠送60G流量。IP稳定且干净，不会因为IP脏被封号。本月白嫖码：鸡你太美  ",
        "url": "https://web4.52pokemon.cc/register?code=qzhkvhLk",
        "gradient": "135deg, #667eea 0%, #764ba2 100%",
        "status": "active"
      },
      {
        "id": "vpn-2",
        "name": "万达云：严测推荐",
        "features": "(36地区，90+节点）海外团队，安全、稳定、极速（支持试用，9折码：wandayun）",
        "url": "https://link.wdyserver.com/register?code=HCmXeijh",
        "gradient": "135deg, #667eea 0%, #764ba2 100%",
        "status": "active"
      },
      {
        "id": "vpn-3",
        "name": "红杏云VPN",
        "features": "老牌VPN提供商了。虽然IP不如宝可梦干净，但是。胜在网速和稳定性和宝可梦旗鼓相当。<br>八折优惠码：hx2025",
        "url": "https://hongxing.one/web/#/login?code=NOGK4o3y",
        "gradient": "135deg, #667eea 0%, #764ba2 100%",
        "status": "active"
      },
      {
        "id": "vpn-4",
        "name": "青云梯：严测推荐",
        "features": "（16地区，70+节点）海外团队，安全稳定极速（月8.5折码：qyt85，年8折码：qyt80）",
        "url": "https://ivt02.qytaff.cc/register?aff=9AOwCUUP",
        "gradient": "135deg, #667eea 0%, #764ba2 100%",
        "status": "active"
      },
      {
        "id": "vpn-5",
        "name": "涅槃云：严测推荐",
        "features": "（16地区，30+节点）严测推荐，海外团队，安全、稳定、极速（9折优惠券：qsy99）",
        "url": "https://theme.revival.baby/register?code=z2B4HAcv",
        "gradient": "135deg, #667eea 0%, #764ba2 100%",
        "status": "active"
      },
      {
        "id": "vpn-6",
        "name": "红杏：严测推荐",
        "features": "(23地区，70+节点）海外团队，安全、稳定、极速（注册即送：50G/30天）（8折优惠码：hongxing666）",
        "url": "https://www.xn--8qv123c.co/auth/register?code=z6kV78AV",
        "gradient": "135deg, #667eea 0%, #764ba2 100%",
        "status": "active"
      },
      {
        "id": "vpn-7",
        "name": "快连VPN：严测推荐",
        "features": "六年老品牌，2000万人的选择，人工客服时时在线，IP干净，速度稳定，价格便宜，通过本站推荐，可以先用再买<br>并且赠送购买时长的20%<br>9折优惠码：380269387",
        "url": "https://8m5tnb.onelink.me/0Iq2/up2p5vb6",
        "gradient": "135deg, #667eea 0%, #764ba2 100%",
        "status": "active"
      }
    ]
  }
}