{
  "total": 75,
  "update_time": "2026-02-24 20:28:50",
  "source_url": "https://ccbaohe.com/appleID/",
  "accounts": [
    {
      "account": "su***@icloud.com",
      "email": "suzannejxj54972@icloud.com",
      "fullEmail": "suzannejxj54972@icloud.com",
      "password": "8kDqBSSRjf",
      "region": "US",
      "regionName": "美国",
      "status": "正常",
      "checkTime": "2026-02-25 04:12:52",
      "crawl_time": "2026-02-24 20:28:50"
    },
    {
      "account": "ll***@icloud.com",
      "email": "lloydmnx97837@icloud.com",
      "fullEmail": "lloydmnx97837@icloud.com",
      "password": "3GSvPsgE2u",
      "region": "US",
      "regionName": "美国",
      "status": "正常",
      "checkTime": "2026-02-25 04:07:28",
      "crawl_time": "2026-02-24 20:28:50"
    },
    {
      "account": "db***@icloud.com",
      "email": "dboedna72553@icloud.com",
      "fullEmail": "dboedna72553@icloud.com",
      "password": "C5Yyb2CmWA",
      "region": "US",
      "regionName": "美国",
      "status": "正常",
      "checkTime": "2026-02-25 04:06:27",
      "crawl_time": "2026-02-24 20:28:50"
    },
    {
      "account": "ur***@icloud.com",
      "email": "uryjose26338@icloud.com",
      "fullEmail": "uryjose26338@icloud.com",
      "password": "nFUs1PVtt6",
      "region": "US",
      "regionName": "美国",
      "status": "正常",
      "checkTime": "2026-02-25 04:05:26",
      "crawl_time": "2026-02-24 20:28:50"
    },
    {
      "account": "ro***@icloud.com",
      "email": "ronaldkkl27343@icloud.com",
      "fullEmail": "ronaldkkl27343@icloud.com",
      "password": "fu2VmjUewW",
      "region": "US",
      "regionName": "美国",
      "status": "正常",
      "checkTime": "2026-02-25 04:04:25",
      "crawl_time": "2026-02-24 20:28:50"
    },
    {
      "account": "ca***@icloud.com",
      "email": "carlaolt40914@icloud.com",
      "fullEmail": "carlaolt40914@icloud.com",
      "password": "QA3km6ZBYT",
      "region": "US",
      "regionName": "美国",
      "status": "正常",
      "checkTime": "2026-02-25 04:12:27",
      "crawl_time": "2026-02-24 20:28:50"
    },
    {
      "account": "ma***@icloud.com",
      "email": "marcelacfe11777@icloud.com",
      "fullEmail": "marcelacfe11777@icloud.com",
      "password": "JwmJ94hX6B",
      "region": "US",
      "regionName": "美国",
      "status": "正常",
      "checkTime": "2026-02-25 04:13:27",
      "crawl_time": "2026-02-24 20:28:50"
    },
    {
      "account": "ro***@icloud.com",
      "email": "robertulf53255@icloud.com",
      "fullEmail": "robertulf53255@icloud.com",
      "password": "bv54ezBCsK",
      "region": "US",
      "regionName": "美国",
      "status": "正常",
      "checkTime": "2026-02-25 04:11:30",
      "crawl_time": "2026-02-24 20:28:50"
    },
    {
      "account": "te***@icloud.com",
      "email": "teresafsf30433@icloud.com",
      "fullEmail": "teresafsf30433@icloud.com",
      "password": "Kq4ja61wpM",
      "region": "US",
      "regionName": "美国",
      "status": "正常",
      "checkTime": "2026-02-25 04:05:49",
      "crawl_time": "2026-02-24 20:28:50"
    },
    {
      "account": "ln***@icloud.com",
      "email": "lnikristie76916@icloud.com",
      "fullEmail": "lnikristie76916@icloud.com",
      "password": "Us4xrBNBck",
      "region": "US",
      "regionName": "美国",
      "status": "正常",
      "checkTime": "2026-02-25 04:10:25",
      "crawl_time": "2026-02-24 20:28:50"
    },
    {
      "account": "di***@icloud.com",
      "email": "dianacbz88614@icloud.com",
      "fullEmail": "dianacbz88614@icloud.com",
      "password": "DEDXfptd4X",
      "region": "US",
      "regionName": "美国",
      "status": "正常",
      "checkTime": "2026-02-25 04:09:26",
      "crawl_time": "2026-02-24 20:28:50"
    },
    {
      "account": "vi***@icloud.com",
      "email": "vincentjohnlamber3k9@icloud.com",
      "fullEmail": "vincentjohnlamber3k9@icloud.com",
      "password": "hNFYn8ZgEY",
      "region": "US",
      "regionName": "美国",
      "status": "正常",
      "checkTime": "2026-02-25 04:14:37",
      "crawl_time": "2026-02-24 20:28:50"
    },
    {
      "account": "al***@icloud.com",
      "email": "alicibrown2z7@icloud.com",
      "fullEmail": "alicibrown2z7@icloud.com",
      "password": "mDbXGQD11x",
      "region": "US",
      "regionName": "美国",
      "status": "正常",
      "checkTime": "2026-02-25 04:14:27",
      "crawl_time": "2026-02-24 20:28:50"
    },
    {
      "account": "fg***@icloud.com",
      "email": "fgrschwartz9j6@icloud.com",
      "fullEmail": "fgrschwartz9j6@icloud.com",
      "password": "VwU6bJECjm",
      "region": "US",
      "regionName": "美国",
      "status": "正常",
      "checkTime": "2026-02-25 04:13:25",
      "crawl_time": "2026-02-24 20:28:50"
    },
    {
      "account": "ir***@icloud.com",
      "email": "irjones7u1@icloud.com",
      "fullEmail": "irjones7u1@icloud.com",
      "password": "nmXt39EQpK",
      "region": "US",
      "regionName": "美国",
      "status": "正常",
      "checkTime": "2026-02-25 04:12:28",
      "crawl_time": "2026-02-24 20:28:50"
    },
    {
      "account": "ti***@icloud.com",
      "email": "timothycasjones2o2@icloud.com",
      "fullEmail": "timothycasjones2o2@icloud.com",
      "password": "Dgn6qXA8nz",
      "region": "US",
      "regionName": "美国",
      "status": "正常",
      "checkTime": "2026-02-25 04:13:29",
      "crawl_time": "2026-02-24 20:28:50"
    },
    {
      "account": "ke***@icloud.com",
      "email": "kellowens5s8@icloud.com",
      "fullEmail": "kellowens5s8@icloud.com",
      "password": "pab4ssSbrQ",
      "region": "US",
      "regionName": "美国",
      "status": "正常",
      "checkTime": "2026-02-25 04:09:26",
      "crawl_time": "2026-02-24 20:28:50"
    },
    {
      "account": "se***@icloud.com",
      "email": "sethbabennett1c6@icloud.com",
      "fullEmail": "sethbabennett1c6@icloud.com",
      "password": "E7NMyhGCrn",
      "region": "US",
      "regionName": "美国",
      "status": "正常",
      "checkTime": "2026-02-25 04:13:26",
      "crawl_time": "2026-02-24 20:28:50"
    },
    {
      "account": "sa***@icloud.com",
      "email": "samanthamolhoffma4c1@icloud.com",
      "fullEmail": "samanthamolhoffma4c1@icloud.com",
      "password": "pEmbZge1X9",
      "region": "US",
      "regionName": "美国",
      "status": "正常",
      "checkTime": "2026-02-25 04:04:28",
      "crawl_time": "2026-02-24 20:28:50"
    },
    {
      "account": "xp***@icloud.com",
      "email": "xpowhayes9g5@icloud.com",
      "fullEmail": "xpowhayes9g5@icloud.com",
      "password": "et1gUBQNjD",
      "region": "US",
      "regionName": "美国",
      "status": "正常",
      "checkTime": "2026-02-25 04:07:27",
      "crawl_time": "2026-02-24 20:28:50"
    },
    {
      "account": "sk***@icloud.com",
      "email": "skinnertsheppard4v1@icloud.com",
      "fullEmail": "skinnertsheppard4v1@icloud.com",
      "password": "e1UU8a5mPb",
      "region": "US",
      "regionName": "美国",
      "status": "正常",
      "checkTime": "2026-02-25 04:10:27",
      "crawl_time": "2026-02-24 20:28:50"
    },
    {
      "account": "fc***@hotmail.com",
      "email": "fcbtyiw070@hotmail.com",
      "fullEmail": "fcbtyiw070@hotmail.com",
      "password": "R3ywBybvGN",
      "region": "US",
      "regionName": "美国",
      "status": "正常",
      "checkTime": "2026-02-25 04:13:29",
      "crawl_time": "2026-02-24 20:28:50"
    },
    {
      "account": "xy***@hotmail.com",
      "email": "xyyvffbji566@hotmail.com",
      "fullEmail": "xyyvffbji566@hotmail.com",
      "password": "4tmCcXcCGY",
      "region": "US",
      "regionName": "美国",
      "status": "正常",
      "checkTime": "2026-02-25 04:12:26",
      "crawl_time": "2026-02-24 20:28:50"
    },
    {
      "account": "da***@icloud.com",
      "email": "dawthomas1k5@icloud.com",
      "fullEmail": "dawthomas1k5@icloud.com",
      "password": "YpFm6AR7YH",
      "region": "US",
      "regionName": "美国",
      "status": "正常",
      "checkTime": "2026-02-25 03:59:49",
      "crawl_time": "2026-02-24 20:28:50"
    },
    {
      "account": "zs***@icloud.com",
      "email": "zsajordan1h1@icloud.com",
      "fullEmail": "zsajordan1h1@icloud.com",
      "password": "jyVx6UZ8Ap",
      "region": "US",
      "regionName": "美国",
      "status": "正常",
      "checkTime": "2026-02-25 04:09:50",
      "crawl_time": "2026-02-24 20:28:50"
    },
    {
      "account": "nb***@hotmail.com",
      "email": "nbrvc11222@hotmail.com",
      "fullEmail": "nbrvc11222@hotmail.com",
      "password": "RVdE5JjDWs",
      "region": "US",
      "regionName": "美国",
      "status": "正常",
      "checkTime": "2025-11-07 12:22:45",
      "crawl_time": "2026-02-24 20:28:50"
    },
    {
      "account": "dp***@hotmail.com",
      "email": "dpkjknd45561@hotmail.com",
      "fullEmail": "dpkjknd45561@hotmail.com",
      "password": "UnM6JFrANs",
      "region": "US",
      "regionName": "美国",
      "status": "正常",
      "checkTime": "2025-11-07 12:39:02",
      "crawl_time": "2026-02-24 20:28:50"
    },
    {
      "account": "je***@icloud.com",
      "email": "jeremiahbentkosk5337@icloud.com",
      "fullEmail": "jeremiahbentkosk5337@icloud.com",
      "password": "yjJbnGu76z",
      "region": "US",
      "regionName": "美国",
      "status": "正常",
      "checkTime": "2026-02-25 04:12:32",
      "crawl_time": "2026-02-24 20:28:50"
    },
    {
      "account": "yv***@gmail.com",
      "email": "yvonnefhunt86291@gmail.com",
      "fullEmail": "yvonnefhunt86291@gmail.com",
      "password": "DPQmB98abY",
      "region": "US",
      "regionName": "美国",
      "status": "正常",
      "checkTime": "2026-02-25 04:10:29",
      "crawl_time": "2026-02-24 20:28:50"
    },
    {
      "account": "au***@icloud.com",
      "email": "augustineserak6313@icloud.com",
      "fullEmail": "augustineserak6313@icloud.com",
      "password": "BZX37QatX8",
      "region": "US",
      "regionName": "美国",
      "status": "正常",
      "checkTime": "2026-02-25 04:07:24",
      "crawl_time": "2026-02-24 20:28:50"
    },
    {
      "account": "fs***@icloud.com",
      "email": "fs2uoo46iph0yic2asn@icloud.com",
      "fullEmail": "fs2uoo46iph0yic2asn@icloud.com",
      "password": "Z4brb7Afeq",
      "region": "CN",
      "regionName": "中国大陆",
      "status": "正常",
      "checkTime": "2026-02-25 04:04:25",
      "crawl_time": "2026-02-24 20:28:50"
    },
    {
      "account": "q6***@icloud.com",
      "email": "q6cfy0de6qsfb4z@icloud.com",
      "fullEmail": "q6cfy0de6qsfb4z@icloud.com",
      "password": "wuuh1TvqUc",
      "region": "HK",
      "regionName": "香港",
      "status": "正常",
      "checkTime": "2026-02-25 02:45:30",
      "crawl_time": "2026-02-24 20:28:50"
    },
    {
      "account": "vw***@icloud.com",
      "email": "vwilkcox5w9@icloud.com",
      "fullEmail": "vwilkcox5w9@icloud.com",
      "password": "vV89nCmZ9F",
      "region": "HK",
      "regionName": "香港",
      "status": "正常",
      "checkTime": "2026-02-25 04:13:30",
      "crawl_time": "2026-02-24 20:28:50"
    },
    {
      "account": "zr***@icloud.com",
      "email": "zrtm03stcmjb6d3yhj@icloud.com",
      "fullEmail": "zrtm03stcmjb6d3yhj@icloud.com",
      "password": "W29zCmfcdH",
      "region": "JP",
      "regionName": "日本",
      "status": "正常",
      "checkTime": "2026-02-25 04:08:28",
      "crawl_time": "2026-02-24 20:28:50"
    },
    {
      "account": "ma***@icloud.com",
      "email": "marywomcdonald5w1@icloud.com",
      "fullEmail": "marywomcdonald5w1@icloud.com",
      "password": "cJTvZAE7M7",
      "region": "HK",
      "regionName": "香港",
      "status": "正常",
      "checkTime": "2026-02-25 04:08:38",
      "crawl_time": "2026-02-24 20:28:50"
    },
    {
      "account": "as***@outlook.com",
      "email": "ashermendez4so@outlook.com",
      "fullEmail": "ashermendez4so@outlook.com",
      "password": "TDxBxQy6WKBy",
      "region": "US",
      "regionName": "美国",
      "status": "正常",
      "checkTime": "2026-02-25 04:02:31",
      "crawl_time": "2026-02-24 20:28:50"
    },
    {
      "account": "ca***@outlook.com",
      "email": "carterhuxuhen@outlook.com",
      "fullEmail": "carterhuxuhen@outlook.com",
      "password": "TDqWzcXC9BRV",
      "region": "US",
      "regionName": "美国",
      "status": "正常",
      "checkTime": "2026-02-25 04:14:20",
      "crawl_time": "2026-02-24 20:28:50"
    },
    {
      "account": "re***@hotmail.com",
      "email": "renatahadnotqw@hotmail.com",
      "fullEmail": "renatahadnotqw@hotmail.com",
      "password": "TDmpRf9JVtPZ",
      "region": "US",
      "regionName": "美国",
      "status": "正常",
      "checkTime": "2026-02-25 03:56:12",
      "crawl_time": "2026-02-24 20:28:50"
    },
    {
      "account": "el***@outlook.com",
      "email": "eliasu2riley@outlook.com",
      "fullEmail": "eliasu2riley@outlook.com",
      "password": "TDhETtb3Adc3",
      "region": "VN",
      "regionName": "越南",
      "status": "正常",
      "checkTime": "2026-02-25 04:04:25",
      "crawl_time": "2026-02-24 20:28:50"
    },
    {
      "account": "wy***@outlook.com",
      "email": "wyattu5kznelson@outlook.com",
      "fullEmail": "wyattu5kznelson@outlook.com",
      "password": "TDQ9u11YA1uV",
      "region": "US",
      "regionName": "美国",
      "status": "正常",
      "checkTime": "2026-02-25 03:58:26",
      "crawl_time": "2026-02-24 20:28:50"
    },
    {
      "account": "wi***@hotmail.com",
      "email": "wilmadaywaltqv@hotmail.com",
      "fullEmail": "wilmadaywaltqv@hotmail.com",
      "password": "TDXNbEp3RMeU",
      "region": "VN",
      "regionName": "越南",
      "status": "正常",
      "checkTime": "2026-02-25 04:07:19",
      "crawl_time": "2026-02-24 20:28:50"
    },
    {
      "account": "eb***@icloud.com",
      "email": "ebjvyyi371878@icloud.com",
      "fullEmail": "ebjvyyi371878@icloud.com",
      "password": "sx5PgRk7DN",
      "region": "CN",
      "regionName": "中国大陆",
      "status": "正常",
      "checkTime": "2026-02-25 04:10:22",
      "crawl_time": "2026-02-24 20:28:50"
    },
    {
      "account": "",
      "email": "5@kuaiyun1.com",
      "fullEmail": "5@kuaiyun1.com",
      "password": "v6VKhXTWtq",
      "region": "VN",
      "regionName": "越南",
      "status": "正常",
      "checkTime": "2026-02-25 04:06:53",
      "crawl_time": "2026-02-24 20:28:50"
    },
    {
      "account": "nw***@icloud.com",
      "email": "nwqmlkm724113@icloud.com",
      "fullEmail": "nwqmlkm724113@icloud.com",
      "password": "HR7XucU1A3",
      "region": "HK",
      "regionName": "香港",
      "status": "正常",
      "checkTime": "2026-02-25 04:09:36",
      "crawl_time": "2026-02-24 20:28:50"
    },
    {
      "account": "ao***@icloud.com",
      "email": "aocflno476251@icloud.com",
      "fullEmail": "aocflno476251@icloud.com",
      "password": "saASwjfq6c",
      "region": "US",
      "regionName": "法国",
      "status": "正常",
      "checkTime": "2026-02-25 04:04:57",
      "crawl_time": "2026-02-24 20:28:50"
    },
    {
      "account": "rm***@icloud.com",
      "email": "rmfwrwv273444@icloud.com",
      "fullEmail": "rmfwrwv273444@icloud.com",
      "password": "1ngfTY1MA4",
      "region": "SG",
      "regionName": "新加坡",
      "status": "正常",
      "checkTime": "2026-02-25 03:57:11",
      "crawl_time": "2026-02-24 20:28:50"
    },
    {
      "account": "hu***@icloud.com",
      "email": "huai284600975@icloud.com",
      "fullEmail": "huai284600975@icloud.com",
      "password": "uc5eTf57JY",
      "region": "TW",
      "regionName": "台湾",
      "status": "正常",
      "checkTime": "2026-02-25 04:14:20",
      "crawl_time": "2026-02-24 20:28:50"
    },
    {
      "account": "rw***@icloud.com",
      "email": "rwvidmf934559@icloud.com",
      "fullEmail": "rwvidmf934559@icloud.com",
      "password": "uP14wNkbPZ",
      "region": "SG",
      "regionName": "新加坡",
      "status": "正常",
      "checkTime": "2026-02-25 04:02:13",
      "crawl_time": "2026-02-24 20:28:50"
    },
    {
      "account": "",
      "email": "7@kuaiyun1.com",
      "fullEmail": "7@kuaiyun1.com",
      "password": "q7m1W4HGNw",
      "region": "TW",
      "regionName": "台湾",
      "status": "正常",
      "checkTime": "2026-02-25 03:51:59",
      "crawl_time": "2026-02-24 20:28:50"
    },
    {
      "account": "ip***@icloud.com",
      "email": "ippekip345080@icloud.com",
      "fullEmail": "ippekip345080@icloud.com",
      "password": "td8fB5fkxC",
      "region": "KR",
      "regionName": "韩国",
      "status": "正常",
      "checkTime": "2026-02-25 03:53:43",
      "crawl_time": "2026-02-24 20:28:50"
    },
    {
      "account": "ip***@icloud.com",
      "email": "ipksauj788181@icloud.com",
      "fullEmail": "ipksauj788181@icloud.com",
      "password": "q3B1e1fjBq",
      "region": "HK",
      "regionName": "香港",
      "status": "正常",
      "checkTime": "2026-02-25 04:12:19",
      "crawl_time": "2026-02-24 20:28:50"
    },
    {
      "account": "sj***@icloud.com",
      "email": "sjejxsq774991@icloud.com",
      "fullEmail": "sjejxsq774991@icloud.com",
      "password": "mbxtWNFYG9",
      "region": "RU",
      "regionName": "俄罗斯",
      "status": "正常",
      "checkTime": "2026-02-25 04:06:40",
      "crawl_time": "2026-02-24 20:28:50"
    },
    {
      "account": "ow***@icloud.com",
      "email": "owegjmt122604@icloud.com",
      "fullEmail": "owegjmt122604@icloud.com",
      "password": "kDrHQgvG4M",
      "region": "VN",
      "regionName": "越南",
      "status": "正常",
      "checkTime": "2026-02-25 03:54:48",
      "crawl_time": "2026-02-24 20:28:50"
    },
    {
      "account": "ju***@icloud.com",
      "email": "jurobpo347962@icloud.com",
      "fullEmail": "jurobpo347962@icloud.com",
      "password": "2shTnUzDsf",
      "region": "US",
      "regionName": "美国",
      "status": "正常",
      "checkTime": "2026-02-25 04:10:35",
      "crawl_time": "2026-02-24 20:28:50"
    },
    {
      "account": "",
      "email": "2@kuaiyun1.com",
      "fullEmail": "2@kuaiyun1.com",
      "password": "eJfMKMKy8Y",
      "region": "US",
      "regionName": "美国",
      "status": "正常",
      "checkTime": "2026-02-25 03:58:34",
      "crawl_time": "2026-02-24 20:28:50"
    },
    {
      "account": "vv***@icloud.com",
      "email": "vvbwbyh472332@icloud.com",
      "fullEmail": "vvbwbyh472332@icloud.com",
      "password": "P7Gn65bKyc",
      "region": "MY",
      "regionName": "马来西亚",
      "status": "正常",
      "checkTime": "2026-02-25 04:12:21",
      "crawl_time": "2026-02-24 20:28:50"
    },
    {
      "account": "li***@icloud.com",
      "email": "li633563763@icloud.com",
      "fullEmail": "li633563763@icloud.com",
      "password": "PNnP6MVmsZ",
      "region": "US",
      "regionName": "美国",
      "status": "正常",
      "checkTime": "2026-02-25 04:14:37",
      "crawl_time": "2026-02-24 20:28:50"
    },
    {
      "account": "ou***@icloud.com",
      "email": "ousdxpf261614@icloud.com",
      "fullEmail": "ousdxpf261614@icloud.com",
      "password": "mXaD3dATKF",
      "region": "VN",
      "regionName": "越南",
      "status": "正常",
      "checkTime": "2026-02-25 04:07:35",
      "crawl_time": "2026-02-24 20:28:50"
    },
    {
      "account": "",
      "email": "6@kuaiyun1.com",
      "fullEmail": "6@kuaiyun1.com",
      "password": "1etbwMQtra",
      "region": "VN",
      "regionName": "越南",
      "status": "正常",
      "checkTime": "2026-02-25 03:55:52",
      "crawl_time": "2026-02-24 20:28:50"
    },
    {
      "account": "bk***@icloud.com",
      "email": "bkm111@icloud.com",
      "fullEmail": "bkm111@icloud.com",
      "password": "dB6XbuMMhb",
      "region": "SG",
      "regionName": "新加坡",
      "status": "正常",
      "checkTime": "2026-02-25 04:10:30",
      "crawl_time": "2026-02-24 20:28:50"
    },
    {
      "account": "sa***@icloud.com",
      "email": "sadrszk050552@icloud.com",
      "fullEmail": "sadrszk050552@icloud.com",
      "password": "9RfENQmqVZ",
      "region": "KR",
      "regionName": "韩国",
      "status": "正常",
      "checkTime": "2026-02-25 03:55:44",
      "crawl_time": "2026-02-24 20:28:50"
    },
    {
      "account": "fu***@icloud.com",
      "email": "fugtdrn021306@icloud.com",
      "fullEmail": "fugtdrn021306@icloud.com",
      "password": "5EYVBqhnev",
      "region": "US",
      "regionName": "土耳其",
      "status": "正常",
      "checkTime": "2026-02-25 03:53:44",
      "crawl_time": "2026-02-24 20:28:50"
    },
    {
      "account": "",
      "email": "8@kuaiyun1.com",
      "fullEmail": "8@kuaiyun1.com",
      "password": "xTt1t1zCRa",
      "region": "TW",
      "regionName": "台湾",
      "status": "正常",
      "checkTime": "2026-02-25 04:01:06",
      "crawl_time": "2026-02-24 20:28:50"
    },
    {
      "account": "wu***@icloud.com",
      "email": "wu985826536225@icloud.com",
      "fullEmail": "wu985826536225@icloud.com",
      "password": "TvV8NvGeBK",
      "region": "US",
      "regionName": "澳大利亚",
      "status": "正常",
      "checkTime": "2026-02-25 04:04:07",
      "crawl_time": "2026-02-24 20:28:50"
    },
    {
      "account": "13***@kuaiyun1.com",
      "email": "13@kuaiyun1.com",
      "fullEmail": "13@kuaiyun1.com",
      "password": "Ktv8yPjYbt",
      "region": "US",
      "regionName": "美国",
      "status": "正常",
      "checkTime": "2026-02-25 04:12:08",
      "crawl_time": "2026-02-24 20:28:50"
    },
    {
      "account": "iv***@icloud.com",
      "email": "ivxtirm369045@icloud.com",
      "fullEmail": "ivxtirm369045@icloud.com",
      "password": "aU1G7CnnuX",
      "region": "US",
      "regionName": "美国",
      "status": "正常",
      "checkTime": "2026-02-25 03:59:18",
      "crawl_time": "2026-02-24 20:28:50"
    },
    {
      "account": "al***@icloud.com",
      "email": "alswlln389627@icloud.com",
      "fullEmail": "alswlln389627@icloud.com",
      "password": "Akm556655",
      "region": "MY",
      "regionName": "马来西亚",
      "status": "正常",
      "checkTime": "2026-02-25 04:11:33",
      "crawl_time": "2026-02-24 20:28:50"
    },
    {
      "account": "wz***@icloud.com",
      "email": "wzradky569773@icloud.com",
      "fullEmail": "wzradky569773@icloud.com",
      "password": "7DqUuSZT2H",
      "region": "HK",
      "regionName": "香港",
      "status": "正常",
      "checkTime": "2026-02-25 04:09:44",
      "crawl_time": "2026-02-24 20:28:50"
    },
    {
      "account": "kd***@icloud.com",
      "email": "kdzibli335026@icloud.com",
      "fullEmail": "kdzibli335026@icloud.com",
      "password": "P2K9pjcW5c",
      "region": "HK",
      "regionName": "香港",
      "status": "正常",
      "checkTime": "2026-02-25 04:11:44",
      "crawl_time": "2026-02-24 20:28:50"
    },
    {
      "account": "ot***@icloud.com",
      "email": "othvtoh347353@icloud.com",
      "fullEmail": "othvtoh347353@icloud.com",
      "password": "NJ8PRT4ga9",
      "region": "CN",
      "regionName": "中国大陆",
      "status": "正常",
      "checkTime": "2026-02-25 04:02:48",
      "crawl_time": "2026-02-24 20:28:50"
    },
    {
      "account": "",
      "email": "9@kuaiyun1.com",
      "fullEmail": "9@kuaiyun1.com",
      "password": "F2tbbcJYH9",
      "region": "TW",
      "regionName": "台湾",
      "status": "正常",
      "checkTime": "2026-02-25 04:00:42",
      "crawl_time": "2026-02-24 20:28:50"
    },
    {
      "account": "zv***@icloud.com",
      "email": "zvmksii070361@icloud.com",
      "fullEmail": "zvmksii070361@icloud.com",
      "password": "F1SA2rVhgw",
      "region": "US",
      "regionName": "美国",
      "status": "正常",
      "checkTime": "2026-02-25 04:13:14",
      "crawl_time": "2026-02-24 20:28:50"
    },
    {
      "account": "kz***@icloud.com",
      "email": "kzfpobt941920@icloud.com",
      "fullEmail": "kzfpobt941920@icloud.com",
      "password": "kZH1nTH9v6",
      "region": "US",
      "regionName": "Unknown",
      "status": "正常",
      "checkTime": "2026-02-25 04:10:13",
      "crawl_time": "2026-02-24 20:28:50"
    },
    {
      "account": "me***@icloud.com",
      "email": "mepjkjy374417@icloud.com",
      "fullEmail": "mepjkjy374417@icloud.com",
      "password": "qzcy6yqUw2",
      "region": "MY",
      "regionName": "马来西亚",
      "status": "正常",
      "checkTime": "2026-02-25 04:10:43",
      "crawl_time": "2026-02-24 20:28:50"
    },
    {
      "account": "jx***@icloud.com",
      "email": "jxjnhgu339891@icloud.com",
      "fullEmail": "jxjnhgu339891@icloud.com",
      "password": "cmGt73MMH2",
      "region": "JP",
      "regionName": "日本",
      "status": "正常",
      "checkTime": "2026-02-25 03:58:48",
      "crawl_time": "2026-02-24 20:28:50"
    }
  ]
}