{
  "total": 41,
  "update_time": "2026-02-24 11:36:20",
  "source_url": "https://ccbaohe.com/appleID/",
  "accounts": [
    {
      "account": "ha***@icloud.com",
      "email": "hartmriggs1q1@icloud.com",
      "fullEmail": "hartmriggs1q1@icloud.com",
      "password": "xz7FTvd4CK",
      "region": "US",
      "regionName": "美国",
      "status": "正常",
      "checkTime": "2026-02-24 19:21:30",
      "crawl_time": "2026-02-24 11:36:20"
    },
    {
      "account": "nb***@hotmail.com",
      "email": "nbrvc11222@hotmail.com",
      "fullEmail": "nbrvc11222@hotmail.com",
      "password": "RVdE5JjDWs",
      "region": "US",
      "regionName": "美国",
      "status": "正常",
      "checkTime": "2025-11-07 12:22:45",
      "crawl_time": "2026-02-24 11:36:20"
    },
    {
      "account": "dp***@hotmail.com",
      "email": "dpkjknd45561@hotmail.com",
      "fullEmail": "dpkjknd45561@hotmail.com",
      "password": "UnM6JFrANs",
      "region": "US",
      "regionName": "美国",
      "status": "正常",
      "checkTime": "2025-11-07 12:39:02",
      "crawl_time": "2026-02-24 11:36:20"
    },
    {
      "account": "ch***@icloud.com",
      "email": "christopherbayers3t7@icloud.com",
      "fullEmail": "christopherbayers3t7@icloud.com",
      "password": "9rz9JPvCPh",
      "region": "US",
      "regionName": "美国",
      "status": "正常",
      "checkTime": "2026-02-24 19:20:47",
      "crawl_time": "2026-02-24 11:36:20"
    },
    {
      "account": "re***@icloud.com",
      "email": "reynoldsdenpayne7e4@icloud.com",
      "fullEmail": "reynoldsdenpayne7e4@icloud.com",
      "password": "bFPf4RxFTC",
      "region": "US",
      "regionName": "美国",
      "status": "正常",
      "checkTime": "2026-02-24 19:20:47",
      "crawl_time": "2026-02-24 11:36:20"
    },
    {
      "account": "ma***@outlook.com",
      "email": "matthewwioakq@outlook.com",
      "fullEmail": "matthewwioakq@outlook.com",
      "password": "bR54696JNb",
      "region": "US",
      "regionName": "美国",
      "status": "正常",
      "checkTime": "2026-02-24 19:20:23",
      "crawl_time": "2026-02-24 11:36:20"
    },
    {
      "account": "el***@outlook.com",
      "email": "elfrieda68waelchiuqv@outlook.com",
      "fullEmail": "elfrieda68waelchiuqv@outlook.com",
      "password": "PJeayx4XyS",
      "region": "TW",
      "regionName": "台湾",
      "status": "正常",
      "checkTime": "2026-02-24 19:29:20",
      "crawl_time": "2026-02-24 11:36:20"
    },
    {
      "account": "ak***@icloud.com",
      "email": "ak13trp10y972767@icloud.com",
      "fullEmail": "ak13trp10y972767@icloud.com",
      "password": "DcTBVhvS9J",
      "region": "HK",
      "regionName": "香港",
      "status": "正常",
      "checkTime": "2026-02-24 19:22:37",
      "crawl_time": "2026-02-24 11:36:20"
    },
    {
      "account": "el***@outlook.com",
      "email": "eliasu2riley@outlook.com",
      "fullEmail": "eliasu2riley@outlook.com",
      "password": "TDGE7da3N9ed",
      "region": "VN",
      "regionName": "越南",
      "status": "正常",
      "checkTime": "2026-02-24 19:07:25",
      "crawl_time": "2026-02-24 11:36:20"
    },
    {
      "account": "wy***@outlook.com",
      "email": "wyattu5kznelson@outlook.com",
      "fullEmail": "wyattu5kznelson@outlook.com",
      "password": "TDM3FEf9asxR",
      "region": "US",
      "regionName": "美国",
      "status": "正常",
      "checkTime": "2026-02-24 19:02:48",
      "crawl_time": "2026-02-24 11:36:20"
    },
    {
      "account": "wi***@hotmail.com",
      "email": "wilmadaywaltqv@hotmail.com",
      "fullEmail": "wilmadaywaltqv@hotmail.com",
      "password": "TDNBPrPsQ89v",
      "region": "VN",
      "regionName": "越南",
      "status": "正常",
      "checkTime": "2026-02-24 19:28:27",
      "crawl_time": "2026-02-24 11:36:20"
    },
    {
      "account": "md***@icloud.com",
      "email": "mdnhmko932097@icloud.com",
      "fullEmail": "mdnhmko932097@icloud.com",
      "password": "Akm556655",
      "region": "MY",
      "regionName": "马来西亚",
      "status": "正常",
      "checkTime": "2026-02-24 02:02:07",
      "crawl_time": "2026-02-24 11:36:20"
    },
    {
      "account": "",
      "email": "2@kuaiyun1.com",
      "fullEmail": "2@kuaiyun1.com",
      "password": "KGWtwA1Tce",
      "region": "US",
      "regionName": "美国",
      "status": "正常",
      "checkTime": "2026-02-24 19:26:22",
      "crawl_time": "2026-02-24 11:36:20"
    },
    {
      "account": "ot***@icloud.com",
      "email": "othvtoh347353@icloud.com",
      "fullEmail": "othvtoh347353@icloud.com",
      "password": "NJ8PRT4ga9",
      "region": "CN",
      "regionName": "中国大陆",
      "status": "正常",
      "checkTime": "2026-02-24 19:13:33",
      "crawl_time": "2026-02-24 11:36:20"
    },
    {
      "account": "ip***@icloud.com",
      "email": "ippekip345080@icloud.com",
      "fullEmail": "ippekip345080@icloud.com",
      "password": "py2UVrApQ1",
      "region": "KR",
      "regionName": "韩国",
      "status": "正常",
      "checkTime": "2026-02-24 19:20:46",
      "crawl_time": "2026-02-24 11:36:20"
    },
    {
      "account": "sa***@icloud.com",
      "email": "sadrszk050552@icloud.com",
      "fullEmail": "sadrszk050552@icloud.com",
      "password": "Sq1EPSktB8",
      "region": "KR",
      "regionName": "韩国",
      "status": "正常",
      "checkTime": "2026-02-24 19:29:54",
      "crawl_time": "2026-02-24 11:36:20"
    },
    {
      "account": "jx***@icloud.com",
      "email": "jxjnhgu339891@icloud.com",
      "fullEmail": "jxjnhgu339891@icloud.com",
      "password": "CTEW9JuMYj",
      "region": "JP",
      "regionName": "日本",
      "status": "正常",
      "checkTime": "2026-02-24 19:26:59",
      "crawl_time": "2026-02-24 11:36:20"
    },
    {
      "account": "sj***@icloud.com",
      "email": "sjejxsq774991@icloud.com",
      "fullEmail": "sjejxsq774991@icloud.com",
      "password": "vgDNYQeDv2",
      "region": "RU",
      "regionName": "俄罗斯",
      "status": "正常",
      "checkTime": "2026-02-24 19:29:20",
      "crawl_time": "2026-02-24 11:36:20"
    },
    {
      "account": "13***@kuaiyun1.com",
      "email": "13@kuaiyun1.com",
      "fullEmail": "13@kuaiyun1.com",
      "password": "HqmUhSEK7Q",
      "region": "US",
      "regionName": "美国",
      "status": "正常",
      "checkTime": "2026-02-24 19:29:54",
      "crawl_time": "2026-02-24 11:36:20"
    },
    {
      "account": "",
      "email": "7@kuaiyun1.com",
      "fullEmail": "7@kuaiyun1.com",
      "password": "EQr8BwNd6v",
      "region": "TW",
      "regionName": "台湾",
      "status": "正常",
      "checkTime": "2026-02-24 19:24:40",
      "crawl_time": "2026-02-24 11:36:20"
    },
    {
      "account": "hu***@icloud.com",
      "email": "huai284600975@icloud.com",
      "fullEmail": "huai284600975@icloud.com",
      "password": "2gesYjw7w3",
      "region": "TW",
      "regionName": "台湾",
      "status": "正常",
      "checkTime": "2026-02-24 19:07:10",
      "crawl_time": "2026-02-24 11:36:20"
    },
    {
      "account": "",
      "email": "6@kuaiyun1.com",
      "fullEmail": "6@kuaiyun1.com",
      "password": "Fqa2ey13qY",
      "region": "VN",
      "regionName": "越南",
      "status": "正常",
      "checkTime": "2026-02-24 19:25:17",
      "crawl_time": "2026-02-24 11:36:20"
    },
    {
      "account": "wu***@icloud.com",
      "email": "wu985826536225@icloud.com",
      "fullEmail": "wu985826536225@icloud.com",
      "password": "brhqWH61nf",
      "region": "US",
      "regionName": "澳大利亚",
      "status": "正常",
      "checkTime": "2026-02-24 19:29:10",
      "crawl_time": "2026-02-24 11:36:20"
    },
    {
      "account": "li***@icloud.com",
      "email": "li633563763@icloud.com",
      "fullEmail": "li633563763@icloud.com",
      "password": "t5aNZYSnpT",
      "region": "US",
      "regionName": "美国",
      "status": "正常",
      "checkTime": "2026-02-24 19:23:02",
      "crawl_time": "2026-02-24 11:36:20"
    },
    {
      "account": "ju***@icloud.com",
      "email": "jurobpo347962@icloud.com",
      "fullEmail": "jurobpo347962@icloud.com",
      "password": "2shTnUzDsf",
      "region": "US",
      "regionName": "美国",
      "status": "正常",
      "checkTime": "2026-02-24 19:22:13",
      "crawl_time": "2026-02-24 11:36:20"
    },
    {
      "account": "kf***@icloud.com",
      "email": "kfobzhl133203@icloud.com",
      "fullEmail": "kfobzhl133203@icloud.com",
      "password": "Akm556655",
      "region": "SG",
      "regionName": "新加坡",
      "status": "正常",
      "checkTime": "2026-02-24 02:12:44",
      "crawl_time": "2026-02-24 11:36:20"
    },
    {
      "account": "ip***@icloud.com",
      "email": "ipksauj788181@icloud.com",
      "fullEmail": "ipksauj788181@icloud.com",
      "password": "Cwezu5qNPV",
      "region": "HK",
      "regionName": "香港",
      "status": "正常",
      "checkTime": "2026-02-24 19:26:18",
      "crawl_time": "2026-02-24 11:36:20"
    },
    {
      "account": "",
      "email": "9@kuaiyun1.com",
      "fullEmail": "9@kuaiyun1.com",
      "password": "1TcAqACQbq",
      "region": "TW",
      "regionName": "台湾",
      "status": "正常",
      "checkTime": "2026-02-24 19:13:12",
      "crawl_time": "2026-02-24 11:36:20"
    },
    {
      "account": "nw***@icloud.com",
      "email": "nwqmlkm724113@icloud.com",
      "fullEmail": "nwqmlkm724113@icloud.com",
      "password": "ZSMSRZd9RK",
      "region": "HK",
      "regionName": "香港",
      "status": "正常",
      "checkTime": "2026-02-24 19:17:02",
      "crawl_time": "2026-02-24 11:36:20"
    },
    {
      "account": "",
      "email": "5@kuaiyun1.com",
      "fullEmail": "5@kuaiyun1.com",
      "password": "563XdMHtKx",
      "region": "VN",
      "regionName": "越南",
      "status": "正常",
      "checkTime": "2026-02-24 19:15:14",
      "crawl_time": "2026-02-24 11:36:20"
    },
    {
      "account": "fu***@icloud.com",
      "email": "fugtdrn021306@icloud.com",
      "fullEmail": "fugtdrn021306@icloud.com",
      "password": "J2e78MvD9N",
      "region": "US",
      "regionName": "土耳其",
      "status": "正常",
      "checkTime": "2026-02-24 19:26:28",
      "crawl_time": "2026-02-24 11:36:20"
    },
    {
      "account": "kz***@icloud.com",
      "email": "kzfpobt941920@icloud.com",
      "fullEmail": "kzfpobt941920@icloud.com",
      "password": "gw9NJ1eNTf",
      "region": "US",
      "regionName": "Unknown",
      "status": "正常",
      "checkTime": "2026-02-24 19:25:50",
      "crawl_time": "2026-02-24 11:36:20"
    },
    {
      "account": "kd***@icloud.com",
      "email": "kdzibli335026@icloud.com",
      "fullEmail": "kdzibli335026@icloud.com",
      "password": "ZU2M3T2eq5",
      "region": "HK",
      "regionName": "香港",
      "status": "正常",
      "checkTime": "2026-02-24 19:22:55",
      "crawl_time": "2026-02-24 11:36:20"
    },
    {
      "account": "ow***@icloud.com",
      "email": "owegjmt122604@icloud.com",
      "fullEmail": "owegjmt122604@icloud.com",
      "password": "3hQpN8ejeZ",
      "region": "VN",
      "regionName": "越南",
      "status": "正常",
      "checkTime": "2026-02-24 19:29:34",
      "crawl_time": "2026-02-24 11:36:20"
    },
    {
      "account": "ou***@icloud.com",
      "email": "ousdxpf261614@icloud.com",
      "fullEmail": "ousdxpf261614@icloud.com",
      "password": "evmYfna2zX",
      "region": "VN",
      "regionName": "越南",
      "status": "正常",
      "checkTime": "2026-02-24 19:10:51",
      "crawl_time": "2026-02-24 11:36:20"
    },
    {
      "account": "iv***@icloud.com",
      "email": "ivxtirm369045@icloud.com",
      "fullEmail": "ivxtirm369045@icloud.com",
      "password": "SAWcjy6ntb",
      "region": "US",
      "regionName": "美国",
      "status": "正常",
      "checkTime": "2026-02-24 19:28:14",
      "crawl_time": "2026-02-24 11:36:20"
    },
    {
      "account": "wz***@icloud.com",
      "email": "wzradky569773@icloud.com",
      "fullEmail": "wzradky569773@icloud.com",
      "password": "aYjz4mNSBq",
      "region": "HK",
      "regionName": "香港",
      "status": "正常",
      "checkTime": "2026-02-24 19:06:25",
      "crawl_time": "2026-02-24 11:36:20"
    },
    {
      "account": "ao***@icloud.com",
      "email": "aocflno476251@icloud.com",
      "fullEmail": "aocflno476251@icloud.com",
      "password": "jn6YtG5AV7",
      "region": "US",
      "regionName": "法国",
      "status": "正常",
      "checkTime": "2026-02-24 19:26:57",
      "crawl_time": "2026-02-24 11:36:20"
    },
    {
      "account": "",
      "email": "8@kuaiyun1.com",
      "fullEmail": "8@kuaiyun1.com",
      "password": "Sj3NJyNR86",
      "region": "JP",
      "regionName": "日本",
      "status": "正常",
      "checkTime": "2026-02-24 19:22:40",
      "crawl_time": "2026-02-24 11:36:20"
    },
    {
      "account": "zv***@icloud.com",
      "email": "zvmksii070361@icloud.com",
      "fullEmail": "zvmksii070361@icloud.com",
      "password": "DKa2pvfmQv",
      "region": "US",
      "regionName": "美国",
      "status": "正常",
      "checkTime": "2026-02-24 19:16:01",
      "crawl_time": "2026-02-24 11:36:20"
    },
    {
      "account": "eb***@icloud.com",
      "email": "ebjvyyi371878@icloud.com",
      "fullEmail": "ebjvyyi371878@icloud.com",
      "password": "X6keef8sfX",
      "region": "CN",
      "regionName": "中国大陆",
      "status": "正常",
      "checkTime": "2026-02-24 19:10:34",
      "crawl_time": "2026-02-24 11:36:20"
    }
  ]
}