[
  {
    "email": "rc67107127067@icloud.com",
    "password": "BnEt5FgUaU",
    "region": "VN"
  },
  {
    "email": "gyrategalactic63799@icloud.com",
    "password": "ZuAW1B5aFq",
    "region": "US"
  },
  {
    "email": "depletesolstice13615@icloud.com",
    "password": "gPwxWe66pM",
    "region": "US"
  },
  {
    "email": "driftconvection7864@icloud.com",
    "password": "nCFa5G3J4N",
    "region": "US"
  },
  {
    "email": "engravecrest50822@icloud.com",
    "password": "kWCJUs4HK3",
    "region": "US"
  },
  {
    "email": "ZanderEvans902f@icloud.com",
    "password": "u8vhqWuXJe",
    "region": "US"
  },
  {
    "email": "KasonKing697k@icloud.com",
    "password": "PHmnfE2CWX",
    "region": "US"
  },
  {
    "email": "NovaLawson139u@icloud.com",
    "password": "VPGmDcV8HE",
    "region": "US"
  },
  {
    "email": "JudeMarsh772z@icloud.com",
    "password": "qQQX85a6FW",
    "region": "US"
  },
  {
    "email": "SageMorris421e@icloud.com",
    "password": "S2C6aMNSUX",
    "region": "US"
  },
  {
    "email": "LennoxMurray053f@icloud.com",
    "password": "DMv9zHGZas",
    "region": "US"
  },
  {
    "email": "RemyPeters690s@icloud.com",
    "password": "g3H919aBKK",
    "region": "US"
  },
  {
    "email": "CaysonReed410h@icloud.com",
    "password": "75D5JmMC3u",
    "region": "US"
  },
  {
    "email": "xiaohuojian66@hotmail.com",
    "password": "bnDTAc1Hnq",
    "region": "US"
  },
  {
    "email": "WilliamMayerdjc@outlook.com.tr",
    "password": "wC3FwXBDD4",
    "region": "US"
  },
  {
    "email": "AidenCarter5367x@icloud.com",
    "password": "urCSu23N4U",
    "region": "US"
  },
  {
    "email": "nbrvc11222@hotmail.com",
    "password": "RVdE5JjDWs",
    "region": "US"
  },
  {
    "email": "dpkjknd45561@hotmail.com",
    "password": "UnM6JFrANs",
    "region": "US"
  },
  {
    "email": "myzpena@hotmail.com",
    "password": "CpAms9yGxJ",
    "region": "US"
  },
  {
    "email": "dolphin7301@hotmail.com",
    "password": "uUWb24PDFg",
    "region": "US"
  },
  {
    "email": "matthewwioakq@outlook.com",
    "password": "yMAXa5Kzuh",
    "region": "US"
  },
  {
    "email": "shroudedzircon13749@icloud.com",
    "password": "e3Twgw2ZAg",
    "region": "US"
  },
  {
    "email": "hirokokom5780@outlook.com",
    "password": "N4VkwZDArx",
    "region": "KR"
  },
  {
    "email": "brucexbradleyyazhx@gmail.com",
    "password": "9W83xhdWyV",
    "region": "CN"
  },
  {
    "email": "ashleeescobar7322ha@outlook.co.th",
    "password": "WWFzw71B6w",
    "region": "TW"
  },
  {
    "email": "henryyfag@hotmail.com",
    "password": "P6GYbY4rWN",
    "region": "JP"
  },
  {
    "email": "anamangottic@hotmail.com",
    "password": "GUwWhEgJ6R",
    "region": "HK"
  },
  {
    "email": "shanjidar6895@hotmail.com",
    "password": "3DpmpCXddu",
    "region": "US"
  },
  {
    "email": "39@laomaos.com",
    "password": "xHdsxv2fMb",
    "region": "US"
  },
  {
    "email": "kshehqmbn@laomaos.com",
    "password": "7qQbBf9Svc",
    "region": "US"
  },
  {
    "email": "ObrienLee9331@outlook.com",
    "password": "TD54BKfCJTSz",
    "region": "US"
  },
  {
    "email": "BrownDavid3023@outlook.com",
    "password": "TDq7HxuPXPgc",
    "region": "US"
  },
  {
    "email": "FieldsThomas4331@outlook.com",
    "password": "TDuUXufRw2De",
    "region": "US"
  },
  {
    "email": "ThomasStephanie7579@outlook.com",
    "password": "TDg8kGuSM2pG",
    "region": "US"
  },
  {
    "email": "CastroRobin2625@outlook.com",
    "password": "TD9t8qK3UbA2",
    "region": "US"
  },
  {
    "email": "MorrisAshley2581@outlook.com",
    "password": "TDcZhBb3MVV6",
    "region": "US"
  },
  {
    "email": "ScottDana2210@outlook.com",
    "password": "TDTBGdhZX8eT",
    "region": "US"
  },
  {
    "email": "GreenBrian3651@outlook.com",
    "password": "TDqYwU3bKkAV",
    "region": "US"
  },
  {
    "email": "7@kuaiyun1.com",
    "password": "jX2ATY7sv8",
    "region": "HK"
  },
  {
    "email": "15@kuaiyun1.com",
    "password": "CNuMg5WYks",
    "region": "TW"
  },
  {
    "email": "14@kuaiyun1.com",
    "password": "x6BVzQF9s7",
    "region": "US"
  },
  {
    "email": "13@kuaiyun1.com",
    "password": "3AKeQ795qy",
    "region": "US"
  },
  {
    "email": "3022@lvoeky.com",
    "password": "XNCw27BAfC",
    "region": "TW"
  },
  {
    "email": "16@kuaiyun1.com",
    "password": "MEwAM76zJd",
    "region": "VN"
  },
  {
    "email": "10@kuaiyun1.com",
    "password": "ZbW8QGDZP1",
    "region": "JP"
  },
  {
    "email": "2@kuaiyun1.com",
    "password": "PzH5hwNGa8",
    "region": "US"
  },
  {
    "email": "1@kuaiyun1.com",
    "password": "DR5pSQkWBP",
    "region": "US"
  },
  {
    "email": "3@kuaiyun1.com",
    "password": "4dXPQaQrku",
    "region": "US"
  },
  {
    "email": "4@kuaiyun1.com",
    "password": "3zbzEwyGdp",
    "region": "US"
  },
  {
    "email": "6@kuaiyun1.com",
    "password": "NrmSK7sNc4",
    "region": "HK"
  },
  {
    "email": "19@kuaiyun1.com",
    "password": "Abq17rRtBW",
    "region": "HK"
  },
  {
    "email": "11@kuaiyun1.com",
    "password": "nd4t8E8WX5",
    "region": "US"
  },
  {
    "email": "17@kuaiyun1.com",
    "password": "3Gy8k1c9HS",
    "region": "KR"
  },
  {
    "email": "3013@lvoeky.com",
    "password": "zt667drPGF",
    "region": "VN"
  },
  {
    "email": "20@kuaiyun1.com",
    "password": "m3KppRrsZB",
    "region": "US"
  },
  {
    "email": "12@kuaiyun1.com",
    "password": "YdnCdtVsR1",
    "region": "US"
  },
  {
    "email": "18@kuaiyun1.com",
    "password": "RyvWYPUCe2",
    "region": "US"
  },
  {
    "email": "5@kuaiyun1.com",
    "password": "jJxj6TW9Xh",
    "region": "US"
  },
  {
    "email": "miastnley@gmail.com",
    "password": "Dd13c8e6d",
    "region": "US"
  },
  {
    "email": "andersenproschvc2764@gmail.com",
    "password": "FAy8cCAE8R",
    "region": "US"
  },
  {
    "email": "qfpcwzp942@163.com",
    "password": "mxhp8mP9BJ",
    "region": "US"
  },
  {
    "email": "madelyncravenlgzx5364@gmail.com",
    "password": "vN151Vd7Dy",
    "region": "US"
  },
  {
    "email": "rowenawoodard246042b@icloud.com",
    "password": "BgW5juwnAt",
    "region": "US"
  },
  {
    "email": "quodonnell@gmail.com",
    "password": "Dd10096da",
    "region": "US"
  },
  {
    "email": "DeborazpiHarr967@icloud.com",
    "password": "x5Qt9ch9m9",
    "region": "US"
  },
  {
    "email": "vgilesgh42@gmail.com",
    "password": "4HWwRkya6B",
    "region": "US"
  },
  {
    "email": "qian2007495zhan@163.com",
    "password": "CkMNTrafY8",
    "region": "US"
  },
  {
    "email": "uchtredmagowandf5018@gmail.com",
    "password": "Y3B9gtum4K",
    "region": "US"
  },
  {
    "email": "KevizpiMe644@icloud.com",
    "password": "jBh1Vj8EH3",
    "region": "US"
  },
  {
    "email": "PerezBettyzzd@gmail.com",
    "password": "98uXd9NR7w",
    "region": "US"
  },
  {
    "email": "kwopigk3809@163.com",
    "password": "Dd128c2e6",
    "region": "US"
  },
  {
    "email": "MirandzpiHugh848@icloud.com",
    "password": "spkV7Q52C1",
    "region": "US"
  },
  {
    "email": "BettyGarcia5be56@gmail.com",
    "password": "44s4nrRa3yZnJ5",
    "region": "US"
  },
  {
    "email": "qfvblj2968@163.com",
    "password": "1qNQ2sDUJ1",
    "region": "US"
  },
  {
    "email": "ancq61nufio@gmail.com",
    "password": "Ma3ZMvZu2w",
    "region": "US"
  },
  {
    "email": "VedderEarlrbpjhf@gmail.com",
    "password": "4PdNahXmqR",
    "region": "US"
  },
  {
    "email": "REBELPRIDE79@hotmail.com",
    "password": "6CFTdyJpNA",
    "region": "US"
  },
  {
    "email": "AllenMilliepyl879@gmail.com",
    "password": "44s41NP3MD5pf3",
    "region": "US"
  },
  {
    "email": "jyvqvepn475@163.com",
    "password": "TDvU2c8Yw9Qr",
    "region": "US"
  },
  {
    "email": "michelleqmrwi3@gmail.com",
    "password": "gM7H6p96py",
    "region": "US"
  },
  {
    "email": "tieshamorwaywi6420@gmail.com",
    "password": "6ZRcWustJ4",
    "region": "US"
  },
  {
    "email": "stevensnjjt1@gmail.com",
    "password": "FP5a6bmVH4",
    "region": "US"
  },
  {
    "email": "jarvarisrivetteuf3409@gmail.com",
    "password": "VG7j2eeg4C",
    "region": "US"
  },
  {
    "email": "qgb477203@163.com",
    "password": "cZK7zCHkFF",
    "region": "US"
  },
  {
    "email": "jy359840651@163.com",
    "password": "Dd1927013",
    "region": "US"
  },
  {
    "email": "orprobeso50@outlook.com",
    "password": "6EJG1crZbk",
    "region": "US"
  },
  {
    "email": "bradtnrosalbav39153@gmail.com",
    "password": "6jRNZT41Bm",
    "region": "US"
  },
  {
    "email": "robertwang380@gmail.com",
    "password": "fgKXq3uWA6",
    "region": "US"
  },
  {
    "email": "rosskennedyjreg5953@gmail.com",
    "password": "De1Hm1h7a9",
    "region": "US"
  },
  {
    "email": "lambertruth282@gmail.com",
    "password": "2fCnKFRFKR",
    "region": "US"
  },
  {
    "email": "pamela53chadwickmjj@outlook.com",
    "password": "ef6BRTCpTj",
    "region": "US"
  }
]