{
  "update_time": "2025-12-22 09:23:09",
  "count": 2,
  "accounts": [
    {
      "account": "20***@kuaiyun1.com",
      "email": "20@kuaiyun1.com",
      "fullEmail": "20@kuaiyun1.com",
      "password": "J4fUzYgXqJ",
      "region": "US",
      "regionName": "澳大利亚",
      "status": "正常",
      "checkTime": "2025-12-22 17:12:07",
      "crawl_time": "2025-12-22 09:23:09"
    },
    {
      "account": "an***@gmail.com",
      "email": "ancq61nufio@gmail.com",
      "fullEmail": "ancq61nufio@gmail.com",
      "password": "Ma3ZMvZu2w",
      "region": "US",
      "regionName": "美国",
      "status": "正常",
      "checkTime": "13分钟前更新",
      "crawl_time": "2025-12-22 09:23:09"
    }
  ]
}