{
  "update_time": "2026-03-17 06:57:31",
  "count": 2,
  "accounts": [
    {
      "account": "sa***@icloud.com",
      "email": "saracortezuqwwr@icloud.com",
      "fullEmail": "saracortezuqwwr@icloud.com",
      "password": "rSUUTu5BcA",
      "region": "VN",
      "regionName": "越南",
      "status": "正常",
      "checkTime": "2026-03-17 14:40:26",
      "crawl_time": "2026-03-17 06:57:31"
    },
    {
      "account": "eu***@icloud.com",
      "email": "eunolga36601@icloud.com",
      "fullEmail": "eunolga36601@icloud.com",
      "password": "11euxx6BTY",
      "region": "VN",
      "regionName": "越南",
      "status": "正常",
      "checkTime": "2026-03-17 14:41:48",
      "crawl_time": "2026-03-17 06:57:31"
    }
  ]
}