{
  "update_time": "2026-01-19 06:30:47",
  "count": 2,
  "accounts": [
    {
      "account": "ep***@icloud.com",
      "email": "epejmmh098979@icloud.com",
      "fullEmail": "epejmmh098979@icloud.com",
      "password": "xmn3fD4NVv",
      "region": "HK",
      "regionName": "香港",
      "status": "正常",
      "checkTime": "2026-01-19 13:54:01",
      "crawl_time": "2026-01-19 06:30:47"
    },
    {
      "account": "an***@gmail.com",
      "email": "andersenproschvc2764@gmail.com",
      "fullEmail": "andersenproschvc2764@gmail.com",
      "password": "FAy8cCAE8R",
      "region": "US",
      "regionName": "美国",
      "status": "正常",
      "checkTime": "18分钟前更新",
      "crawl_time": "2026-01-19 06:30:47"
    }
  ]
}