{
  "update_time": "2026-01-01 06:25:49",
  "count": 2,
  "accounts": [
    {
      "account": "ja***@gmail.com",
      "email": "jarvarisrivetteuf3409@gmail.com",
      "fullEmail": "jarvarisrivetteuf3409@gmail.com",
      "password": "VG7j2eeg4C",
      "region": "US",
      "regionName": "美国",
      "status": "正常",
      "checkTime": "22分钟前更新",
      "crawl_time": "2026-01-01 06:25:49"
    },
    {
      "account": "Ti***@icloud.com",
      "email": "TillyHo28illt@icloud.com",
      "fullEmail": "TillyHo28illt@icloud.com",
      "password": "kZnFsCfs1B",
      "region": "US",
      "regionName": "美国",
      "status": "正常",
      "checkTime": "2026-01-01 14:16:42",
      "crawl_time": "2026-01-01 06:25:49"
    }
  ]
}