{
  "update_time": "2026-02-07 14:20:39",
  "count": 2,
  "accounts": [
    {
      "account": "um***@icloud.com",
      "email": "umnm3qnwbzujfiu3ws@icloud.com",
      "fullEmail": "umnm3qnwbzujfiu3ws@icloud.com",
      "password": "fKpf23a61Q",
      "region": "US",
      "regionName": "美国",
      "status": "正常",
      "checkTime": "2026-02-07 22:06:23",
      "crawl_time": "2026-02-07 14:20:39"
    },
    {
      "account": "et***@icloud.com",
      "email": "etzgemcx253vmcmd@icloud.com",
      "fullEmail": "etzgemcx253vmcmd@icloud.com",
      "password": "VygTp64qf1",
      "region": "US",
      "regionName": "美国",
      "status": "正常",
      "checkTime": "2026-02-07 21:39:22",
      "crawl_time": "2026-02-07 14:20:39"
    }
  ]
}