{
  "update_time": "2026-02-17 04:13:50",
  "count": 2,
  "accounts": [
    {
      "account": "ma***@icloud.com",
      "email": "marcelacfe11777@icloud.com",
      "fullEmail": "marcelacfe11777@icloud.com",
      "password": "FQcA9haxyQ",
      "region": "US",
      "regionName": "美国",
      "status": "正常",
      "checkTime": "2026-02-17 11:53:01",
      "crawl_time": "2026-02-17 04:13:50"
    },
    {
      "account": "ow***@icloud.com",
      "email": "owegjmt122604@icloud.com",
      "fullEmail": "owegjmt122604@icloud.com",
      "password": "nWsSznK1Gq",
      "region": "HK",
      "regionName": "香港",
      "status": "正常",
      "checkTime": "2026-02-17 11:56:15",
      "crawl_time": "2026-02-17 04:13:50"
    }
  ]
}